{
    "Ar36": {
        "error": 0.0005988724242464488, 
        "filter_outliers_dict": {
            "filter_outliers": true, 
            "iterations": 2, 
            "std_devs": 2
        }, 
        "fit": "Parabolic", 
        "value": 0.06473750260270789
    }, 
    "Ar37": {
        "error": 0.013846359874500525, 
        "filter_outliers_dict": {
            "filter_outliers": true, 
            "iterations": 2, 
            "std_devs": 2
        }, 
        "fit": "linear", 
        "value": 32.08468109033322
    }, 
    "Ar38": {
        "error": 0.013196443234544135, 
        "filter_outliers_dict": {
            "filter_outliers": true, 
            "iterations": 2, 
            "std_devs": 2
        }, 
        "fit": "linear", 
        "value": 0.2756750289934027
    }, 
    "Ar39": {
        "error": 0.026262426316531525, 
        "filter_outliers_dict": {
            "filter_outliers": true, 
            "iterations": 2, 
            "std_devs": 2
        }, 
        "fit": "Parabolic", 
        "value": 21.15679895233474
    }, 
    "Ar40": {
        "error": 0.021700869338108494, 
        "filter_outliers_dict": {
            "filter_outliers": true, 
            "iterations": 2, 
            "std_devs": 2
        }, 
        "fit": "Parabolic", 
        "value": 21.935543901489822
    }
}